awscatalyst/__init__.py
awscatalyst/aws.py
awscatalyst/awslambda.py
awscatalyst/cfn.py
awscatalyst/ec2.py
awscatalyst/exceptions.py
awscatalyst/s3.py
awscatalyst/temp.py
awscatalyst/util.py
awscatalyst/version.py
awscatalyst-0.0.9.dist-info/DESCRIPTION.rst
awscatalyst-0.0.9.dist-info/METADATA
awscatalyst-0.0.9.dist-info/RECORD
awscatalyst-0.0.9.dist-info/WHEEL
awscatalyst-0.0.9.dist-info/metadata.json
awscatalyst-0.0.9.dist-info/top_level.txt
