Metadata-Version: 2.0
Name: awscatalyst
Version: 0.0.9
Summary: boto3 wrapper to make AWS DevOps' life easier
Home-page: https://github.com/clifflu/awscatalyst
Author: Cliff Chao-kuan Lu
Author-email: clifflu@gmail.com
License: MIT
Keywords: boto3 aws
Platform: UNKNOWN
Classifier: Development Status :: 3 - Alpha
Classifier: Intended Audience :: Developers
Classifier: License :: OSI Approved :: MIT License
Classifier: Programming Language :: Python :: 2
Classifier: Programming Language :: Python :: 2.6
Classifier: Programming Language :: Python :: 2.7
Classifier: Programming Language :: Python :: 3
Classifier: Programming Language :: Python :: 3.3
Classifier: Programming Language :: Python :: 3.4
Classifier: Programming Language :: Python :: 3.5
Requires-Dist: boto3
Requires-Dist: jinja2
Provides-Extra: test
Requires-Dist: pytest; extra == 'test'
Requires-Dist: pytest-cov; extra == 'test'
Requires-Dist: pytest-xdist; extra == 'test'
